simple-pyper/__init__.py
simple-pyper/inspector.py
simple-pyper/main.py
simple_pyper/__init__.py
simple_pyper/inspector.py
simple_pyper/main.py
simple_pyper-0.1.0.dist-info/LICENSE
simple_pyper-0.1.0.dist-info/METADATA
simple_pyper-0.1.0.dist-info/WHEEL
simple_pyper-0.1.0.dist-info/entry_points.txt
simple_pyper-0.1.0.dist-info/top_level.txt
simple_pyper-0.1.0.dist-info/zip-safe
simple_pyper-0.1.0.dist-info/RECORD
